postalclient/__init__.py
postalclient/main.py
postalclient/test.py
postal_client-0.0.7.dist-info/METADATA
postal_client-0.0.7.dist-info/WHEEL
postal_client-0.0.7.dist-info/top_level.txt
postal_client-0.0.7.dist-info/RECORD
